README.rst
setup.py
7xydothis.egg-info/PKG-INFO
7xydothis.egg-info/SOURCES.txt
7xydothis.egg-info/dependency_links.txt
7xydothis.egg-info/top_level.txt
something/__init__.py