Metadata-Version: 1.0
Name: 7xydothis
Version: 0.1
Summary: Utitilies to use the APIs
Home-page: https://github.com/frkb/7xydothis
Author: bernardfrk
Author-email: bernard.frk@gmail.com
License: UNKNOWN
Platform: UNKNOWN
